oat_tools/__init__.py
oat_tools/captions.py
oat_tools/cli.py
oat_tools/references.py
oat_tools/wordcounter.py
oat_tools-1.1.3.dist-info/METADATA
oat_tools-1.1.3.dist-info/WHEEL
oat_tools-1.1.3.dist-info/entry_points.txt
oat_tools-1.1.3.dist-info/RECORD
