Metadata-Version: 2.4
Name: oat-tools
Version: 1.1.3
Summary: OAT Tools is a CLI for managing Oppimispäiväkirja Markdown files.
Author-email: Jani Sourander <jani.sourander@kamk.fi>
Requires-Python: >=3.13
Requires-Dist: click>=8.2.1
Requires-Dist: tabulate>=0.9.0
